carbon_txt/__init__.py
carbon_txt/cli.py
carbon_txt/exceptions.py
carbon_txt/finders.py
carbon_txt/hookspecs.py
carbon_txt/log_config.py
carbon_txt/parsers_toml.py
carbon_txt/plugins.py
carbon_txt/process_csrd_document.py
carbon_txt/processors.py
carbon_txt/validators.py
carbon_txt/schemas/__init__.py
carbon_txt/schemas/common.py
carbon_txt/schemas/version_0_2.py
carbon_txt/schemas/version_0_3.py
carbon_txt/schemas/version_0_4.py
carbon_txt/web/__init__.py
carbon_txt/web/api.py
carbon_txt/web/manage.py
carbon_txt/web/middleware.py
carbon_txt/web/config/__init__.py
carbon_txt/web/config/asgi.py
carbon_txt/web/config/urls.py
carbon_txt/web/config/wsgi.py
carbon_txt/web/config/settings/__init__.py
carbon_txt/web/config/settings/base.py
carbon_txt/web/config/settings/development.py
carbon_txt/web/config/settings/production.py
carbon_txt/web/config/settings/test.py
carbon_txt/web/validation_logging/__init__.py
carbon_txt/web/validation_logging/middleware.py
carbon_txt/web/validation_logging/models.py
carbon_txt/web/validation_logging/migrations/0001_initial.py
carbon_txt/web/validation_logging/migrations/0002_validationlogentry_source_and_more.py
carbon_txt/web/validation_logging/migrations/__init__.py
carbon_txt-0.0.24.dist-info/METADATA
carbon_txt-0.0.24.dist-info/WHEEL
carbon_txt-0.0.24.dist-info/entry_points.txt
carbon_txt-0.0.24.dist-info/licenses/LICENSE
carbon_txt-0.0.24.dist-info/RECORD
