Metadata-Version: 2.4
Name: carbon-txt
Version: 0.0.24
Summary: A command line tool containing a validator for carbon.txt files, by the Green Web Foundation
Author: Chris Adams, Hannah Smith, Fershad Irani, Tim Cowlishaw
License: Apache-2.0
License-File: LICENSE
Classifier: License :: OSI Approved :: Apache Software License
Requires-Python: >=3.11
Requires-Dist: arelle-release>=2.36.3
Requires-Dist: django-cors-headers>=4.6.0
Requires-Dist: django-environ>=0.11.2
Requires-Dist: django-ninja>=1.3.0
Requires-Dist: django-structlog>=9.0.0
Requires-Dist: django-stubs[compatible-mypy]>=5.1.1
Requires-Dist: dnspython>=2.7.0
Requires-Dist: granian>=1.6.2
Requires-Dist: httpx>=0.27.2
Requires-Dist: pluggy>=1.5.0
Requires-Dist: pydantic-extra-types>=2.10.3
Requires-Dist: rich>=13.9.2
Requires-Dist: sentry-sdk[django]>=2.18.0
Requires-Dist: tldextract>=5.3.0
Requires-Dist: typer>=0.12.5
